radiotherapyai/LICENSE
radiotherapyai/__init__.py
radiotherapyai/__main__.py
radiotherapyai/_build.py
radiotherapyai-0.1.0.dist-info/entry_points.txt
radiotherapyai-0.1.0.dist-info/LICENSE
radiotherapyai-0.1.0.dist-info/WHEEL
radiotherapyai-0.1.0.dist-info/METADATA
radiotherapyai-0.1.0.dist-info/RECORD
