Metadata-Version: 2.1
Name: radiotherapyai
Version: 0.1.0
Summary: AI assisted treatments accessible to all
License: Apache-2.0
Author: Simon Biggs
Author-email: simon.biggs@radiotherapy.ai
Requires-Python: >=3.9,<4.0
Classifier: License :: OSI Approved :: Apache Software License
Classifier: Programming Language :: Python :: 3
Classifier: Programming Language :: Python :: 3.10
Classifier: Programming Language :: Python :: 3.9
